setup.py
property_based_testing/__init__.py
property_based_testing/__main__.py
property_based_testing/api.py
property_based_testing/dependency.py
property_based_testing/internal.py
property_based_testing/make_property_test.py
property_based_testing/py.typed
property_based_testing/test_result.py
property_based_testing.egg-info/PKG-INFO
property_based_testing.egg-info/SOURCES.txt
property_based_testing.egg-info/dependency_links.txt
property_based_testing.egg-info/top_level.txt
property_based_testing/discovery/__init__.py
property_based_testing/discovery/parse_test_suite.py
test_property_based_testing/__init__.py
test_property_based_testing/code_to_test_with.py
test_property_based_testing/test_inject.py
test_property_based_testing/test_discovery/__init__.py
test_property_based_testing/test_discovery/empty_test_suite.py
test_property_based_testing/test_discovery/property_test_suite_with_one_failing_test.py
test_property_based_testing/test_discovery/property_test_suite_with_one_non_test.py
test_property_based_testing/test_discovery/property_test_suite_with_one_test.py
test_property_based_testing/test_discovery/test_parse_suite.py